shareithub/__init__.py
shareithub/shareithub.py
shareithub-3.2.1.dist-info/METADATA
shareithub-3.2.1.dist-info/WHEEL
shareithub-3.2.1.dist-info/top_level.txt
shareithub-3.2.1.dist-info/RECORD
