Metadata-Version: 2.2
Name: shareithub
Version: 3.2.1
Summary: Don't forget to join us at: SHARE IT HUB
Home-page: https://github.com/shareithub
Author: SHARE IT HUB
Author-email: 
Classifier: Programming Language :: Python :: 3
Classifier: License :: OSI Approved :: MIT License
Classifier: Operating System :: OS Independent
Requires-Python: >=3.6
Dynamic: author
Dynamic: classifier
Dynamic: description
Dynamic: description-content-type
Dynamic: home-page
Dynamic: requires-python
Dynamic: summary
